{"id": "asyncio.locks", "path": "/home/alan/.pyenv/versions/3.7.9/envs/aliby/lib/python3.7/site-packages/mypy/typeshed/stdlib/asyncio/locks.pyi", "mtime": 1643375656, "size": 2758, "hash": "8d23ebb0619c3f17ed2faa8b647dc92b05b37826f5d23627a57e87a7c20a59f4", "data_mtime": 1654510508, "dependencies": ["sys", "collections", "types", "typing", "asyncio.events", "asyncio.futures", "builtins", "abc"], "suppressed": [], "options": {"disallow_untyped_calls": false, "warn_unused_ignores": false, "disallow_any_decorated": false, "implicit_reexport": true, "bazel": false, "disallow_any_unimported": false, "strict_optional": true, "always_false": [], "warn_unreachable": false, "warn_return_any": false, "disallow_any_expr": false, "platform": "linux", "disallow_untyped_decorators": false, "ignore_errors": false, "strict_optional_whitelist": null, "check_untyped_defs": false, "mypyc": false, "allow_untyped_globals": false, "local_partial_types": false, "ignore_missing_imports": false, "plugins": [], "no_implicit_optional": false, "allow_redefinition": false, "follow_imports_for_stubs": false, "follow_imports": "normal", "disallow_incomplete_defs": false, "disallow_subclassing_any": false, "disallow_any_explicit": false, "warn_no_return": true, "disallow_any_generics": false, "always_true": [], "strict_equality": false, "show_none_errors": true, "disallow_untyped_defs": false}, "dep_prios": [10, 5, 5, 5, 5, 5, 5, 30], "dep_lines": [1, 2, 3, 4, 6, 7, 1, 1], "interface_hash": "6759ef8a08f850adc898a9cab595202e25740955e02288e296d02ef39ed4e05b", "version_id": "0.930", "ignore_all": true, "plugin_data": null}